LICENSE
MANIFEST.in
Makefile
README
mangler.py
setup.cfg
setup.py
tiddlywebconfig.py
test/__init__.py
test/__init__.pyc
test/test_cascade.py
test/test_compile.py
test/test_gamut.py
test/test_geo.py
test/test_search.py
test/__pycache__/test_cascade.cpython-27-PYTEST.pyc
test/__pycache__/test_compile.cpython-27-PYTEST.pyc
test/__pycache__/test_gamut.cpython-27-PYTEST.pyc
test/__pycache__/test_geo.cpython-27-PYTEST.pyc
test/__pycache__/test_search.cpython-27-PYTEST.pyc
tiddlywebplugins/__init__.py
tiddlywebplugins.mysql3.egg-info/PKG-INFO
tiddlywebplugins.mysql3.egg-info/SOURCES.txt
tiddlywebplugins.mysql3.egg-info/dependency_links.txt
tiddlywebplugins.mysql3.egg-info/namespace_packages.txt
tiddlywebplugins.mysql3.egg-info/not-zip-safe
tiddlywebplugins.mysql3.egg-info/requires.txt
tiddlywebplugins.mysql3.egg-info/top_level.txt
tiddlywebplugins/mysql3/__init__.py