Metadata-Version: 1.0
Name: tiddlywebplugins.mysql3
Version: 3.1.0
Summary: MySQL-based store for tiddlyweb
Home-page: http://pypi.python.org/pypi/tiddlywebplugins.mysql3
Author: Chris Dent
Author-email: cdent@peermore.com
License: BSD
Platform: Posix; MacOS X; Windows
